syncache
