Metadata-Version: 1.1
Name: syncache
Version: 0.2.1
Summary: Synchronization Cache for Grid Computing
Home-page: https://github.com/pakozm/syncache
Author: Francisco Zamora-Martinez
Author-email: pakozm@gmail.com
License: MIT
Download-URL: https://github.com/pakozm/syncache/tarball/0.2.1
Keywords: rsync,cache
Platform: UNKNOWN
Classifier: Development Status :: 3 - Alpha
Classifier: Intended Audience :: Developers
Classifier: Programming Language :: Python
Classifier: Programming Language :: Python :: 2
Classifier: Programming Language :: Python :: 2.6
Classifier: Programming Language :: Python :: 2.7
